.gitignore
LICENSE.txt
MANIFEST.in
README.md
setup.py
solargraph_utils/__init__.py
solargraph_utils/core.py
solargraph_utils/helpers.py
solargraph_utils.py.egg-info/PKG-INFO
solargraph_utils.py.egg-info/SOURCES.txt
solargraph_utils.py.egg-info/dependency_links.txt
solargraph_utils.py.egg-info/top_level.txt