Metadata-Version: 1.0
Name: solargraph-utils.py
Version: 1.1.0
Summary: solargraph-utils for python
Home-page: https://github.com/uplus/solargraph-utils.py
Author: uplus
Author-email: UNKNOWN
License: The MIT License (MIT)
